observing_strategy/__init__.py
observing_strategy/observing_strategy.py
observing_strategy-0.0.1.dist-info/AUTHORS.rst
observing_strategy-0.0.1.dist-info/LICENSE
observing_strategy-0.0.1.dist-info/METADATA
observing_strategy-0.0.1.dist-info/WHEEL
observing_strategy-0.0.1.dist-info/top_level.txt
observing_strategy-0.0.1.dist-info/RECORD
