Metadata-Version: 2.1
Name: observing-strategy
Version: 0.0.1
Summary: A package
Home-page: https://github.com/j-faria/observing_strategy
Author: João Faria
Author-email: joao.faria@astro.up.pt
License: MIT license
Keywords: observing_strategy
Platform: UNKNOWN
Classifier: Development Status :: 2 - Pre-Alpha
Classifier: Intended Audience :: Developers
Classifier: License :: OSI Approved :: MIT License
Classifier: Natural Language :: English
Classifier: Programming Language :: Python :: 3
Classifier: Programming Language :: Python :: 3.5
Classifier: Programming Language :: Python :: 3.6
Classifier: Programming Language :: Python :: 3.7
Classifier: Programming Language :: Python :: 3.8
Requires-Python: >=3.5
